{
  "rood": "rood",
  "rode": "rood",
  "red": "rood",
  "kleur rood": "rood",
  "rood licht": "rood",
  "blauw": "blauw",
  "blauwe": "blauw",
  "kleur blauw": "blauw",
  "blauw licht": "blauw",
  "blue": "blauw",
  "groen": "groen",
  "groene": "groen",
  "kleur groen": "groen",
  "groen licht": "groen",
  "green": "groen",
  "geel": "geel",
  "gele": "geel",
  "heel": "geel",
  "kleur geel": "geel",
  "geel licht": "geel",
  "yellow": "geel",
  "paars": "paars",
  "paarse": "paars",
  "paar": "paars",
  "kleur paars": "paars",
  "paars licht": "paars",
  "purple": "paars",
  "oranje": "oranje",
  "oranje kleur": "oranje",
  "oranje licht": "oranje",
  "orange": "oranje",
  "roze": "roze",
  "pink": "roze",
  "kleur roze": "roze",
  "roze licht": "roze",
  "wit": "wit",
  "witte": "wit",
  "kleur wit": "wit",
  "wit licht": "wit",
  "white": "wit",
  "aan": "aan",
  "on": "aan",
  "aanzetten": "aan",
  "zet aan": "aan",
  "aan zetten": "aan",
  "licht aan": "aan",
  "uit": "uit",
  "off": "uit",
  "uitzetten": "uit",
  "zet uit": "uit",
  "uit zetten": "uit",
  "licht uit": "uit",
  "regenboog": "regenboog",
  "rainbow": "regenboog",
  "termodus": "termodus",
  "knippert": "knipperen",
  "knippering": "knipperen",
  "flash": "knipperen"
}
